<?xml version='1.0' encoding='UTF-8'?> 
<zabbix_export> 
	<version>5.2</version> 
	<date>2021-11-23T22:54:46Z</date> 
	<groups> 
		<group> 
			<name>rack6.4</name> 
		</group> 
	</groups> 
	<hosts> 
<host>
	<host>R-AA-FATTY30</host>
	<name>R-AA-FATTY30</name>
	<groups>
	<group>
	<name>rack6.4</name>
	</group>
	</groups>
	<interfaces>
	<interface>
	<ip>10.209.68.30</ip>	<interface_ref>if1</interface_ref>
	</interface>
	</interfaces>
	<inventory_mode>DISABLED</inventory_mode>
</host>
<host>
	<host>HULK08</host>
	<name>HULK08</name>
	<groups>
	<group>
	<name>rack6.4</name>
	</group>
	</groups>
	<interfaces>
	<interface>
	<ip>10.210.9.154</ip>	<interface_ref>if1</interface_ref>
	</interface>
	</interfaces>
	<inventory_mode>DISABLED</inventory_mode>
</host>
<host>
	<host>HULK07</host>
	<name>HULK07</name>
	<groups>
	<group>
	<name>rack6.4</name>
	</group>
	</groups>
	<interfaces>
	<interface>
	<ip>10.210.9.156</ip>	<interface_ref>if1</interface_ref>
	</interface>
	</interfaces>
	<inventory_mode>DISABLED</inventory_mode>
</host>
<host>
	<host>R-SW-HULK11</host>
	<name>R-SW-HULK11</name>
	<groups>
	<group>
	<name>rack6.4</name>
	</group>
	</groups>
	<interfaces>
	<interface>
	<ip>10.224.12.56</ip>	<interface_ref>if1</interface_ref>
	</interface>
	</interfaces>
	<inventory_mode>DISABLED</inventory_mode>
</host>

 	</hosts> 
</zabbix_export>  
